zocalo/__init__.py
zocalo/py.typed
zocalo/wrapper.py
zocalo/cli/__init__.py
zocalo/cli/configure_rabbitmq.py
zocalo/cli/dlq_check.py
zocalo/cli/dlq_purge.py
zocalo/cli/dlq_reinject.py
zocalo/cli/go.py
zocalo/cli/pickup.py
zocalo/cli/queue_drain.py
zocalo/cli/shutdown.py
zocalo/cli/wrap.py
zocalo/configuration/__init__.py
zocalo/configuration/argparse.py
zocalo/configuration/plugin_graylog.py
zocalo/configuration/plugin_jmx.py
zocalo/configuration/plugin_logging.py
zocalo/configuration/plugin_rabbitmqapi.py
zocalo/configuration/plugin_slurm.py
zocalo/configuration/plugin_smtp.py
zocalo/configuration/plugin_storage.py
zocalo/service/__init__.py
zocalo/service/dispatcher.py
zocalo/service/jsonlines.py
zocalo/service/mailer.py
zocalo/service/schlockmeister.py
zocalo/util/__init__.py
zocalo/util/jmxstats.py
zocalo/util/rabbitmq.py
zocalo/util/symlink.py
zocalo/util/slurm/__init__.py
zocalo/util/slurm/models.py
zocalo-1.3.0.dist-info/licenses/AUTHORS.rst
zocalo-1.3.0.dist-info/licenses/LICENSE
zocalo-1.3.0.dist-info/METADATA
zocalo-1.3.0.dist-info/WHEEL
zocalo-1.3.0.dist-info/entry_points.txt
zocalo-1.3.0.dist-info/top_level.txt
zocalo-1.3.0.dist-info/RECORD
