Metadata-Version: 2.4
Name: zocalo
Version: 1.3.0
Summary: Infrastructure components for automated data processing at Diamond Light Source
Author-email: Nicholas Devenish <ndevenish@gmail.com>
Project-URL: Bug-Tracker, https://github.com/DiamondLightSource/python-zocalo/issues
Project-URL: Changelog, https://github.com/DiamondLightSource/python-zocalo/blob/main/HISTORY.rst
Project-URL: Documentation, https://github.com/DiamondLightSource/python-zocalo
Project-URL: Download, https://github.com/DiamondLightSource/python-zocalo/releases
Project-URL: GitHub, https://github.com/DiamondLightSource/python-zocalo
Requires-Python: >=3.11
License-File: LICENSE
License-File: AUTHORS.rst
Requires-Dist: pyyaml
Requires-Dist: graypy
Requires-Dist: marshmallow
Requires-Dist: requests
Requires-Dist: pydantic<3,>=2
Requires-Dist: workflows>=3.0
Dynamic: license-file
